Verilog/mealy/mealy.v
module mealy #(
    //Parameters
    parameter IDLE   = 2'b00,
    parameter wait_a = 2'b01,
    parameter wait_b = 2'b10,
    parameter wait_c = 2'b11
) (
    // Inputs
    input clk,
    reset,
    start,
    done_a,
    done_b,
    done_c,

    output reg start_a,
    start_b,
    start_c,
    done
);

  //regs
  reg [1:0] state;
  reg [1:0] state_nxt;

  always @(posedge clk) begin
    state <= #1 (reset ? IDLE : state_nxt);
  end


  always @(*) begin
    start_a = 0;
    start_b = 0;
    start_c = 0;
    done    = 0;
    state_nxt = state;
    case (state)
      IDLE:
      if (start) begin
        state_nxt = wait_a;
        start_a   = 1;
      end
      wait_a:
      if (done_a) begin
        state_nxt = wait_b;
        start_b   = 1;
      end
      wait_b:
      if (done_b) begin
        state_nxt = wait_c;
        start_c   = 1;
      end
      wait_c:
      if (done_c) begin
        state_nxt = IDLE;
        done = 1;
      end
      default: state_nxt = state;  // hold current state
    endcase
  end
endmodule

Verilog/mealy/tb_mealy.v
module tb_mealy;

  reg
      clk,
      reset,
      start,
      done_a,
      done_b,
      done_c;  // The inputs of the test module must have to declare reg
  wire start_a, start_b, start_c, done;  // The outputs needs to decleare nets

  mealy uut (
      .clk(clk),
      .reset(reset),
      .start(start),
      .done_a(done_a),
      .done_b(done_b),
      .done_c(done_c),
      .start_a(start_a),
      .start_b(start_b),
      .start_c(start_c),
      .done(done)
  );

  initial begin
    clk = 1;
    forever begin
      #5 clk = ~clk;
    end
  end

  initial begin
    reset  = 0;
    start  = 0;
    done_a = 0;
    done_b = 0;
    done_c = 0;

    $dumpvars(2, tb_mealy);
    $dumpfile("wave.vcd");

    @(posedge clk);
    reset <= #1 1;
    @(posedge clk);
    reset <= #1 0;

    repeat (5) @(posedge clk);
    start <= #1 1;
    @(posedge clk);
    start <= #1 0;

    repeat (5) @(posedge clk);
    done_a <= #1 1;
    @(posedge clk);
    done_a <= #1 0;

    repeat (5) @(posedge clk);
    done_b <= #1 1;
    @(posedge clk);
    done_b <= #1 0;

    repeat (5) @(posedge clk);
    done_c <= #1 1;
    #2 $display("done : %d ", done);
    @(posedge clk);
    done_c <= #1 0;
    repeat (10) @(posedge clk);

    $finish;
  end
endmodule

Verilog/mealy/dump.vcd
$date
	Tue Oct 31 22:52:36 2023
$end
$version
	Icarus Verilog
$end
$timescale
	1s
$end
$scope module tb_mealy $end
$var wire 1 ! start_c $end
$var wire 1 " start_b $end
$var wire 1 # start_a $end
$var wire 1 $ done $end
$var reg 1 % clk $end
$var reg 1 & done_a $end
$var reg 1 ' done_b $end
$var reg 1 ( done_c $end
$var reg 1 ) reset $end
$var reg 1 * start $end
$scope module uut $end
$var wire 1 % clk $end
$var wire 1 & done_a $end
$var wire 1 ' done_b $end
$var wire 1 ( done_c $end
$var wire 1 ) reset $end
$var wire 1 * start $end
$var reg 1 $ done $end
$var reg 1 # start_a $end
$var reg 1 " start_b $end
$var reg 1 ! start_c $end
$var reg 2 + state [1:0] $end
$var reg 2 , state_nxt [1:0] $end
$upscope $end
$upscope $end
$enddefinitions $end
#0
$dumpvars
bx ,
bx +
0*
0)
0(
0'
0&
1%
0$
0#
0"
0!
$end
#5
0%
#10
1%
#11
1)
#15
0%
#20
1%
#21
b0 ,
b0 +
0)
#25
0%
#30
1%
#35
0%
#40
1%
#45
0%
#50
1%
#55
0%
#60
1%
#65
0%
#70
1%
#71
1#
b1 ,
1*
#75
0%
#80
1%
#81
0#
b1 +
0*
#85
0%
#90
1%
#95
0%
#100
1%
#105
0%
#110
1%
#115
0%
#120
1%
#125
0%
#130
1%
#131
1"
b10 ,
1&
#135
0%
#140
1%
#141
0"
b10 +
0&
#145
0%
#150
1%
#155
0%
#160
1%
#165
0%
#170
1%
#175
0%
#180
1%
#185
0%
#190
1%
#191
1!
b11 ,
1'
#195
0%
#200
1%
#201
0!
b11 +
0'
#205
0%
#210
1%
#215
0%
#220
1%
#225
0%
#230
1%
#235
0%
#240
1%
#245
0%
#250
1%
#251
1$
b0 ,
1(
#255
0%
#260
1%
#261
0$
b0 +
0(
